fenix/__init__.py
fenix/aliceblue.py
fenix/angelone.py
fenix/choice.py
fenix/finvasia.py
fenix/fivepaisa.py
fenix/fyers.py
fenix/iifl.py
fenix/kotak.py
fenix/kotakneo.py
fenix/kunjee.py
fenix/mastertrust.py
fenix/motilaloswal.py
fenix/paper.py
fenix/symphony.py
fenix/upstox.py
fenix/vpc.py
fenix/zerodha.py
fenix/base/__init__.py
fenix/base/broker.py
fenix/base/constants.py
fenix/base/errors.py
fenix-1.0.5.dist-info/LICENSE
fenix-1.0.5.dist-info/METADATA
fenix-1.0.5.dist-info/WHEEL
fenix-1.0.5.dist-info/top_level.txt
fenix-1.0.5.dist-info/RECORD
