Metadata-Version: 2.1
Name: fenix
Version: 1.0.5
Summary: A Python library for trading in the Indian Finance Sector with support for multiple broker APIs.
Home-page: https://fenix.hardeep.tech
Author: Hardeep Singh
Author-email: Hardeep Singh <hardeep.hd13@gmail.com>
Maintainer-email: Hardeep Singh <hardeep.hd13@gmail.com>
License: GNU GENERAL PUBLIC LICENSE
Project-URL: Homepage, https://fenix.hardeep.tech
Project-URL: Documentation, https://github.com/TheHardeep/fenix/fenix/wiki
Project-URL: Repository, https://github.com/TheHardeep/fenix.git
Keywords: fenix,aliceblue,angelone,choice,finvasia,fivepaisa,fyers,iifl,kotak,kotakneo,kunjee,mastertrust,motilaloswal,paper,symphony,upstox,vpc,zerodha,finance,broker,trader,XTS,kite,algorithmic,algotrading,api,arbitrage,real-time,realtime,backtest,backtesting,etc,framework,invest,investing,investor,library,market,market data,ohlcv,order,orderbook,order book,strategy,ticker,tickers,toolkit,trade,trader,trading,volume,websocket,websockets,web socket,web sockets,ws
Classifier: Development Status :: 4 - Beta
Classifier: Intended Audience :: Developers
Classifier: Intended Audience :: Financial and Insurance Industry
Classifier: Intended Audience :: Information Technology
Classifier: Topic :: Software Development :: Build Tools
Classifier: Topic :: Office/Business :: Financial :: Investment
Classifier: License :: OSI Approved :: GNU General Public License v3 (GPLv3)
Classifier: Programming Language :: Python :: 3.8
Classifier: Programming Language :: Python :: 3.9
Classifier: Programming Language :: Python :: 3.10
Classifier: Programming Language :: Python :: 3.11
Classifier: Operating System :: OS Independent
Classifier: Environment :: Console
Requires-Python: >=3.8
License-File: LICENSE
Requires-Dist: cryptography >=42.0.5
Requires-Dist: numpy >=1.24.4
Requires-Dist: pandas >=2.0.3
Requires-Dist: pycryptodome >=3.20.0
Requires-Dist: PyJWT >=2.8.0
Requires-Dist: pyotp >=2.9.0
Requires-Dist: requests >=2.31.0
Requires-Dist: requests-oauthlib >=1.4.0
Requires-Dist: selenium >=4.18.1
Requires-Dist: urllib3 >=2.2.1
Requires-Dist: webdriver-manager >=4.0.1
Requires-Dist: undetected-chromedriver >=3.5.5
